shoobx.wfmc-4.3.2-py3.10-nspkg.pth
shoobx/wfmc/README.txt
shoobx/wfmc/__init__.py
shoobx/wfmc/attributeintegration.py
shoobx/wfmc/deadline.txt
shoobx/wfmc/deadline.xpdl
shoobx/wfmc/interfaces.py
shoobx/wfmc/process.py
shoobx/wfmc/publication-1.0.xpdl
shoobx/wfmc/publication-2.1-duplicate-Deadline.xpdl
shoobx/wfmc/publication-2.1-duplicate-ExtendedAttribute.xpdl
shoobx/wfmc/publication-2.1-script.xpdl
shoobx/wfmc/publication-2.1.xpdl
shoobx/wfmc/subflow.txt
shoobx/wfmc/subflow.xpdl
shoobx/wfmc/tests.py
shoobx/wfmc/xpdl-2.1.txt
shoobx/wfmc/xpdl.py
shoobx/wfmc/xpdl.txt
shoobx/wfmc/adapter/__init__.py
shoobx/wfmc/adapter/integration.py
shoobx/wfmc/adapter/integration.txt
shoobx/wfmc/adapter/tests.py
shoobx.wfmc-4.3.2.dist-info/METADATA
shoobx.wfmc-4.3.2.dist-info/WHEEL
shoobx.wfmc-4.3.2.dist-info/namespace_packages.txt
shoobx.wfmc-4.3.2.dist-info/top_level.txt
shoobx.wfmc-4.3.2.dist-info/RECORD
