Metadata-Version: 2.1
Name: shoobx.wfmc
Version: 4.3.2
Summary: Workflow-Management Coalition Workflow Engine
Home-page: http://pypi.python.org/pypi/shoobx.wfmc
Author: Zope Corporation and Contributors
Author-email: zope3-dev@zope.org
License: ZPL 2.1
Keywords: bpmn wfmc xpdl workflow engine
Classifier: Development Status :: 5 - Production/Stable
Classifier: Intended Audience :: Developers
Classifier: License :: OSI Approved :: Zope Public License
Classifier: Programming Language :: Python
Classifier: Programming Language :: Python :: 3
Classifier: Programming Language :: Python :: 3.7
Classifier: Programming Language :: Python :: 3.8
Classifier: Programming Language :: Python :: 3.9
Classifier: Programming Language :: Python :: 3.10
Classifier: Programming Language :: Python :: 3.11
Classifier: Programming Language :: Python :: Implementation :: CPython
Classifier: Natural Language :: English
Classifier: Operating System :: OS Independent
Requires-Dist: setuptools
Requires-Dist: zope.component
Requires-Dist: persistent
Requires-Dist: zope.cachedescriptors
Provides-Extra: test
Requires-Dist: coverage ; extra == 'test'
Requires-Dist: zope.testing ; extra == 'test'
Requires-Dist: zope.testrunner ; extra == 'test'
